setup.py
treelogger4mongo/__init__.py
treelogger4mongo/branch.py
treelogger4mongo/tree.py
treelogger4mongo.egg-info/PKG-INFO
treelogger4mongo.egg-info/SOURCES.txt
treelogger4mongo.egg-info/dependency_links.txt
treelogger4mongo.egg-info/top_level.txt