Metadata-Version: 1.1
Name: treelogger4mongo
Version: 0.1.0
Summary: A logger that logs in a tree structure form in mongo
Home-page: https://github.com/TheThing/treelogger4mongo
Author: Jonatan Nilsson
Author-email: jonatan@nilsson.is
License: WTFPL-2
Platform: UNKNOWN
Classifier: Development Status :: 3 - Alpha
Classifier: Environment :: Console
Classifier: Environment :: Web Environment
Classifier: Intended Audience :: Developers
Classifier: Intended Audience :: System Administrators
Classifier: License :: OSI Approved :: BSD License
Classifier: Operating System :: OS Independent
Classifier: Programming Language :: Python
Classifier: Topic :: Utilities
Classifier: Topic :: System :: Logging
Requires: pymongo
